[
  {
    "photo1": "https://upload.wikimedia.org/wikipedia/fr/thumb/4/4c/Asteras_Tripolis_FC_logo.svg/2048px-Asteras_Tripolis_FC_logo.svg.png",
    "name1": "Asteras Tripolis",
    "photo2": "https://upload.wikimedia.org/wikipedia/en/7/70/Panionios_FC.png",
    "name2": "Panionios",
    "champ": "Coupe de Grèce",
    "heure": "16H00",
    "date": "08/01/2025",
    "pro": "Total: (+1.5)"
  },
  {
    "photo1": "https://upload.wikimedia.org/wikipedia/fr/thumb/8/84/Panathinaikos_F.C._logo.svg/1200px-Panathinaikos_F.C._logo.svg.png",
    "name1": "Panathinaikos",
    "photo2": "https://upload.wikimedia.org/wikipedia/fr/thumb/e/e9/Atromitos.png/320px-Atromitos.png",
    "name2": "Atromitos",
    "champ": "Coupe de Grèce",
    "heure": "18H30",
    "date": "08/01/2025",
    "pro": "V1"
  },
  {
    "photo1": "https://upload.wikimedia.org/wikipedia/en/thumb/a/a2/SL_Benfica_logo.svg/1200px-SL_Benfica_logo.svg.png",
    "name1": "Benfica",
    "photo2": "https://upload.wikimedia.org/wikipedia/en/thumb/7/79/S.C._Braga_logo.svg/1200px-S.C._Braga_logo.svg.png",
    "name2": "Braga",
    "champ": "Portugal. Coupe de la Ligue",
    "heure": "19H45",
    "date": "08/01/2025",
    "pro": "Deux équipes vont marquer: OUI"
  },
    {
    "photo1": "https://upload.wikimedia.org/wikipedia/fr/thumb/e/e0/Royal_Antwerp_Football_Club_%28logo%29.svg/1200px-Royal_Antwerp_Football_Club_%28logo%29.svg.png",
    "name1": "Royal Antwerp",
    "photo2": "https://upload.wikimedia.org/wikipedia/en/0/02/Royale_Union_Saint-Gilloise_logo.png",
    "name2": "Royale Union",
    "champ": "Coupe de Belgique",
    "heure": "19H45",
    "date": "08/01/2025",
    "pro": "12"
  },
    {
    "photo1": "https://upload.wikimedia.org/wikipedia/en/thumb/d/de/Trabzonspor_Amblem.svg/1200px-Trabzonspor_Amblem.svg.png",
    "name1": "Trabzonspor",
    "photo2": "https://upload.wikimedia.org/wikipedia/en/thumb/4/40/Alanyaspor_logo.svg/1200px-Alanyaspor_logo.svg.png",
    "name2": "Alanyaspor",
    "champ": "Coupe de Turquie",
    "heure": "15H00",
    "date": "08/01/2025",
    "pro": "Total: (+1.5)"
  }
]
