
  [
  {
    "photo1": "https://upload.wikimedia.org/wikipedia/en/thumb/1/19/Stade_de_Reims_logo.svg/1200px-Stade_de_Reims_logo.svg.png",
    "name1": "Stade de Reims",
    "photo2": "https://upload.wikimedia.org/wikipedia/commons/thumb/4/4a/FC_Metz_2021_Logo.svg/1200px-FC_Metz_2021_Logo.svg.png",
    "name2": "Metz",
    "champ": "France. Qualification",
    "heure": "18H30",
    "date": "29/05/2025",
    "pro": "Total: (+1.5)"
  },  
  {
    "photo1": "https://upload.wikimedia.org/wikipedia/fr/thumb/e/e0/Royal_Antwerp_Football_Club_%28logo%29.svg/1200px-Royal_Antwerp_Football_Club_%28logo%29.svg.png",
    "name1": "Royal Antwerp",
    "photo2": "https://upload.wikimedia.org/wikipedia/fr/thumb/9/93/Sporting_de_Charleroi_%28logo%29.svg/1200px-Sporting_de_Charleroi_%28logo%29.svg.png",
    "name2": "R.Charleroi",
    "champ": "Belgique. Jupiler Ligue",
    "heure": "16H30",
    "date": "29/05/2025",
    "pro": "Total: (+1.5)"
  },
  {
    "photo1": "https://upload.wikimedia.org/wikipedia/commons/thumb/a/a2/LASK-Logo_2023.svg/1200px-LASK-Logo_2023.svg.png",
    "name1": "LASK Linz",
    "photo2": "https://encrypted-tbn0.gstatic.com/images?q=tbn:ANd9GcSIUJ8HUB6SO_9z3h9X-0rU7sd2KtXOW25wqw&s",
    "name2": "Rapid Vienne",
    "champ": "Autriche. Bundesliga",
    "heure": "15H00",
    "date": "29/05/2025",
    "pro": "Total: (+2)"
  },
    {
    "photo1": "https://encrypted-tbn0.gstatic.com/images?q=tbn:ANd9GcStxzoeiAAJbuVoVAaJ3Q0Qcyqwu2Rg1c3_HA&s",
    "name1": "SC Telstar",
    "photo2": "https://upload.wikimedia.org/wikipedia/fr/thumb/f/f4/Logo_Willem_II_Tilburg_-_2022.svg/1200px-Logo_Willem_II_Tilburg_-_2022.svg.png",
    "name2": "Willem",
    "champ": "Pays-Bas. Qualification",
    "heure": "18H00",
    "date": "29/05/2025",
    "pro": "12"
  },
  {
    "photo1": "https://upload.wikimedia.org/wikipedia/fr/thumb/4/4f/Logo_FC_Copenhagen_2023.svg/2048px-Logo_FC_Copenhagen_2023.svg.png",
    "name1": "Copenhague",
    "photo2": "https://encrypted-tbn0.gstatic.com/images?q=tbn:ANd9GcSkzb0TRqhxNcKVGNndhklq8OlGqxZ-UlPRmA&s",
    "name2": "Silkeborg",
    "champ": "Coupe du Danemark",
    "heure": "15H00",
    "date": "29/05/2025",
    "pro": "1X Et TP(1.5) - OUI"
  },
  {
    "photo1": "https://upload.wikimedia.org/wikipedia/en/thumb/e/e1/US_Cremonese_logo.svg/1200px-US_Cremonese_logo.svg.png",
    "name1": "Cremonese",
    "photo2": "https://upload.wikimedia.org/wikipedia/commons/thumb/a/aa/Spezia_Calcio.svg/640px-Spezia_Calcio.svg.png",
    "name2": "Spezia",
    "champ": "Italie. Série B",
    "heure": "18H30",
    "date": "29/05/2025",
    "pro": "Total: (+1.5)"
  },
  {
    "photo1": "https://upload.wikimedia.org/wikipedia/commons/thumb/7/71/Brann_logo.svg/2560px-Brann_logo.svg.png",
    "name1": "Brann",
    "photo2": "https://upload.wikimedia.org/wikipedia/commons/thumb/5/57/Molde_Fotball_Logo.svg/1200px-Molde_Fotball_Logo.svg.png",
    "name2": "Molde",
    "champ": "Norvège. Eliteserien",
    "heure": "16H00",
    "date": "29/05/2025",
    "pro": "Deux équipes vont marquer: OUI"
  },
  {
    "photo1": "https://upload.wikimedia.org/wikipedia/fr/thumb/7/77/Logo_IF_Brommapojkarna_2020.svg/1200px-Logo_IF_Brommapojkarna_2020.svg.png",
    "name1": "Brommapojkarna",
    "photo2": "https://upload.wikimedia.org/wikipedia/commons/thumb/e/e6/Djurgardens_IF_logo.svg/1200px-Djurgardens_IF_logo.svg.png",
    "name2": "Djurgardens",
    "champ": "Suède. Allsvenskan",
    "heure": "16H00",
    "date": "29/05/2025",
    "pro": "Total: (+2)"
  },
    {
    "photo1": "https://encrypted-tbn0.gstatic.com/images?q=tbn:ANd9GcQDion0MxdsQqq05b2S9RNO92JBTM-GmdxnsA&s",
    "name1": "Malmo",
    "photo2": "https://upload.wikimedia.org/wikipedia/en/thumb/5/5d/BK_Hacken_logo.svg/1200px-BK_Hacken_logo.svg.png",
    "name2": "Hächen",
    "champ": "Coupe de Suède",
    "heure": "13H00",
    "date": "29/05/2025",
    "pro": "Total: (+2)"
  },
    {
    "photo1": "https://upload.wikimedia.org/wikipedia/en/e/e1/FC_Livyi_Bereh_Kyiv_logo.png",
    "name1": "Levyy Bereg Kyiv",
    "photo2": "https://upload.wikimedia.org/wikipedia/commons/b/bc/FC_Metalist_1925_Kharkiv_logo.png",
    "name2": "Metallist 1925",
    "champ": "Ukraine. Premier-Liha",
    "heure": "15H00",
    "date": "29/05/2025",
    "pro": "Total: (+1.5)"
  }
]
