[
  {
    "photo1": "https://encrypted-tbn0.gstatic.com/images?q=tbn:ANd9GcSk15S4jklXjKYTAiPAoLXLcN2T72RrSDepmCQb0ePNhw&s=10",
    "name1": "Qarabag",
    "photo2": "https://upload.wikimedia.org/wikipedia/commons/thumb/8/8d/CSKA_Sofia_logo.svg/1920px-CSKA_Sofia_logo.svg.png",
    "name2": "CSKA Sofia",
    "champ": "Ligue Europa de l'UEFA",
    "heure": "16H00",
    "date": "23/07/2026",
    "pro": "1X"
  },
     {
    "photo1": "https://upload.wikimedia.org/wikipedia/commons/thumb/d/df/FC_Dynamo_Kyiv_logo.svg/330px-FC_Dynamo_Kyiv_logo.svg.png",
    "name1": "Dynamo Kyiv",
    "photo2": "https://upload.wikimedia.org/wikipedia/fr/thumb/9/92/PAOK_FC_logo.svg/1920px-PAOK_FC_logo.svg.png",
    "name2": "PAOK",
    "champ": "Ligue Europa de l'UEFA",
    "heure": "17H00",
    "date": "23/07/2026",
    "pro": "Total: (+1.5)"
  },
    {
    "photo1": "https://upload.wikimedia.org/wikipedia/fr/thumb/8/84/Logo_Troms%C3%B8_IL_2020.svg/960px-Logo_Troms%C3%B8_IL_2020.svg.png?_=20241213152102",
    "name1": "Tromso",
    "photo2": "https://upload.wikimedia.org/wikipedia/pt/4/4d/FC_Hradec_Kr%C3%A1lov%C3%A9_logo.png",
    "name2": "Hradec Kralove",
    "champ": "Ligue Europa de l'UEFA",
    "heure": "17H00",
    "date": "23/07/2026",
    "pro": "Total: (+1.5)"
  },
  {
    "photo1": "https://upload.wikimedia.org/wikipedia/fr/thumb/a/ab/Logo_Hammarby_IF.svg/1280px-Logo_Hammarby_IF.svg.png",
    "name1": "Hammarby",
    "photo2": "https://encrypted-tbn0.gstatic.com/images?q=tbn:ANd9GcTnyO1dOzBo8UgWvhvKyccodVGP-AB__0ARpHNmufl36Q&s=10",
    "name2": "Anderlecht",
    "champ": "Ligue Europa de l'UEFA",
    "heure": "17H00",
    "date": "23/07/2026",
    "pro": "Total: (+1.5)"
  },
  {
    "photo1": "https://upload.wikimedia.org/wikipedia/commons/thumb/e/e3/FC_St._Gallen_logo.svg/500px-FC_St._Gallen_logo.svg.png",
    "name1": "Saint-Gall",
    "photo2": "https://encrypted-tbn0.gstatic.com/images?q=tbn:ANd9GcTVEAFluaEkwZI2GIgit5NMI0tBG6Sx-UmLRH8Vo-gujA&s=10",
    "name2": "Benfica",
    "champ": "Ligue Europa de l'UEFA",
    "heure": "18H00",
    "date": "23/07/2026",
    "pro": "2X"
  }
]
